LICENSE
README.rst
setup.py
abed/__init__.py
abed/__version__.py
abed/auto.py
abed/compress.py
abed/conf.py
abed/constants.py
abed/datasets.py
abed/exceptions.py
abed/fab.py
abed/fab_util.py
abed/git_util.py
abed/help.py
abed/init.py
abed/io.py
abed/local.py
abed/models.py
abed/pbs.py
abed/progress.py
abed/prune.py
abed/run.py
abed/run_utils.py
abed/tasks.py
abed/ui.py
abed/utils.py
abed/zips.py
abed.egg-info/PKG-INFO
abed.egg-info/SOURCES.txt
abed.egg-info/dependency_links.txt
abed.egg-info/requires.txt
abed.egg-info/top_level.txt
abed/html/__init__.py
abed/html/common.py
abed/html/index.py
abed/html/main.py
abed/html/metric_tables.py
abed/html/rank_graphs.py
abed/html/rank_tests.py
abed/html/scalar_tables.py
abed/html/utils.py
abed/html/view.py
abed/results/__init__.py
abed/results/assess.py
abed/results/cache.py
abed/results/cv_tt.py
abed/results/export.py
abed/results/main.py
abed/results/models.py
abed/results/ranks.py
abed/results/significance.py
abed/results/tables.py
abed/results/walk.py
bin/abed
share/data/DataTables-1.10.7/extensions/AutoFill/css/dataTables.autoFill.css
share/data/DataTables-1.10.7/extensions/AutoFill/css/dataTables.autoFill.min.css
share/data/DataTables-1.10.7/extensions/AutoFill/examples/columns.html
share/data/DataTables-1.10.7/extensions/AutoFill/examples/complete-callback.html
share/data/DataTables-1.10.7/extensions/AutoFill/examples/fill-both.html
share/data/DataTables-1.10.7/extensions/AutoFill/examples/fill-horizontal.html
share/data/DataTables-1.10.7/extensions/AutoFill/examples/index.html
share/data/DataTables-1.10.7/extensions/AutoFill/examples/scrolling.html
share/data/DataTables-1.10.7/extensions/AutoFill/examples/simple.html
share/data/DataTables-1.10.7/extensions/AutoFill/examples/step-callback.html
share/data/DataTables-1.10.7/extensions/AutoFill/images/filler.png
share/data/DataTables-1.10.7/extensions/AutoFill/js/dataTables.autoFill.js
share/data/DataTables-1.10.7/extensions/AutoFill/js/dataTables.autoFill.min.js
share/data/DataTables-1.10.7/extensions/ColReorder/css/dataTables.colReorder.css
