Metadata-Version: 2.1
Name: abed
Version: 0.1.3
Summary: A command line tool for easily managing benchmark experiments
Home-page: https://github.com/GjjvdBurg/abed
Author: Gertjan van den Burg
Author-email: gertjanvandenburg@gmail.com
License: GPLv2
Platform: UNKNOWN
Classifier: License :: OSI Approved :: GNU General Public License v2 (GPLv2)
Classifier: Programming Language :: Python
Classifier: Programming Language :: Python :: 3
Classifier: Programming Language :: Python :: 3.6
Classifier: Programming Language :: Python :: Implementation :: CPython
Classifier: Programming Language :: Python :: Implementation :: PyPy
Classifier: Intended Audience :: Science/Research
Classifier: Topic :: Scientific/Engineering
Classifier: Topic :: Utilities
Requires-Python: >=3.4.0
Provides-Extra: docs
Provides-Extra: tests
Provides-Extra: dev
License-File: LICENSE
